prompt_dedent/__init__.py
prompt_dedent/dedent.py
prompt_dedent-0.1.0.dist-info/METADATA
prompt_dedent-0.1.0.dist-info/WHEEL
prompt_dedent-0.1.0.dist-info/top_level.txt
prompt_dedent-0.1.0.dist-info/RECORD
