Metadata-Version: 2.4
Name: prompt_dedent
Version: 0.1.0
Summary: A library for writing multi-line strings with proper indentation in Python code
Author-email: Ray Li <rl.invent@gmail.com>
License: MIT
Project-URL: Homepage, https://github.com/ray-li/prompt_dedent
Project-URL: Documentation, https://github.com/ray-li/prompt_dedent#readme
Project-URL: Repository, https://github.com/ray-li/prompt_dedent
Project-URL: Issues, https://github.com/ray-li/prompt_dedent/issues
Keywords: string,formatting,indentation,dedent,multiline
Classifier: Development Status :: 4 - Beta
Classifier: Intended Audience :: Developers
Classifier: License :: OSI Approved :: MIT License
Classifier: Programming Language :: Python :: 3
Classifier: Programming Language :: Python :: 3.8
Classifier: Programming Language :: Python :: 3.9
Classifier: Programming Language :: Python :: 3.10
Classifier: Programming Language :: Python :: 3.11
Classifier: Programming Language :: Python :: 3.12
Classifier: Topic :: Software Development :: Libraries :: Python Modules
Classifier: Topic :: Text Processing
Requires-Python: >=3.8
